analytic_continuation_server/__init__.py
analytic_continuation_server/app.py
analytic_continuation_server/cli.py
analytic_continuation_server/codegen.py
analytic_continuation_server/config.py
analytic_continuation_server/converters.py
analytic_continuation_server/models.py
analytic_continuation_server/session_state.py
analytic_continuation_server/routes/__init__.py
analytic_continuation_server/routes/domaincolor.py
analytic_continuation_server/routes/health.py
analytic_continuation_server/routes/laurent.py
analytic_continuation_server/routes/meromorphic.py
analytic_continuation_server/routes/session.py
analytic_continuation_server/routes/transform.py
analytic_continuation_server-0.1.0.dist-info/METADATA
analytic_continuation_server-0.1.0.dist-info/WHEEL
analytic_continuation_server-0.1.0.dist-info/entry_points.txt
analytic_continuation_server-0.1.0.dist-info/licenses/LICENSE
analytic_continuation_server-0.1.0.dist-info/RECORD
