Metadata-Version: 2.4
Name: analytic-continuation-server
Version: 0.1.0
Summary: FastAPI server for domain coloring visualization, coordinate transforms, Laurent fitting, and analytic continuation
Project-URL: Homepage, https://github.com/egoughnour/analytic-continuation-server
Project-URL: Documentation, https://analytic-continuation-server.readthedocs.io
Project-URL: Repository, https://github.com/egoughnour/analytic-continuation-server
Project-URL: Issues, https://github.com/egoughnour/analytic-continuation-server/issues
Author: Erik Goughnour
License-Expression: MIT
License-File: LICENSE
Keywords: analytic-continuation,api-server,complex-analysis,domain-coloring,fastapi,laurent-series,visualization
Classifier: Development Status :: 4 - Beta
Classifier: Framework :: FastAPI
Classifier: Intended Audience :: Developers
Classifier: Intended Audience :: Science/Research
Classifier: License :: OSI Approved :: MIT License
Classifier: Operating System :: OS Independent
Classifier: Programming Language :: Python :: 3
Classifier: Programming Language :: Python :: 3.10
Classifier: Programming Language :: Python :: 3.11
Classifier: Programming Language :: Python :: 3.12
Classifier: Topic :: Internet :: WWW/HTTP :: HTTP Servers
Classifier: Topic :: Scientific/Engineering :: Mathematics
Classifier: Topic :: Scientific/Engineering :: Visualization
Classifier: Typing :: Typed
Requires-Python: >=3.10
Requires-Dist: analytic-continuation>=0.1.0
Requires-Dist: fastapi>=0.100.0
Requires-Dist: pydantic>=2.0.0
Requires-Dist: uvicorn[standard]>=0.22.0
Provides-Extra: all
Requires-Dist: httpx>=0.24.0; extra == 'all'
Requires-Dist: numpy>=1.20.0; extra == 'all'
Requires-Dist: pillow>=9.0.0; extra == 'all'
Requires-Dist: py-domaincolor>=0.1.0; extra == 'all'
Requires-Dist: pytest-asyncio>=0.21.0; extra == 'all'
Requires-Dist: pytest-cov>=4.0.0; extra == 'all'
Requires-Dist: pytest>=7.0.0; extra == 'all'
Requires-Dist: sphinx-autodoc-typehints>=1.20.0; extra == 'all'
Requires-Dist: sphinx-rtd-theme>=1.0.0; extra == 'all'
Requires-Dist: sphinx>=6.0.0; extra == 'all'
Provides-Extra: dev
Requires-Dist: httpx>=0.24.0; extra == 'dev'
Requires-Dist: pytest-asyncio>=0.21.0; extra == 'dev'
Requires-Dist: pytest-cov>=4.0.0; extra == 'dev'
Requires-Dist: pytest>=7.0.0; extra == 'dev'
Requires-Dist: sphinx-autodoc-typehints>=1.20.0; extra == 'dev'
Requires-Dist: sphinx-rtd-theme>=1.0.0; extra == 'dev'
Requires-Dist: sphinx>=6.0.0; extra == 'dev'
Provides-Extra: docs
Requires-Dist: sphinx-autodoc-typehints>=1.20.0; extra == 'docs'
Requires-Dist: sphinx-rtd-theme>=1.0.0; extra == 'docs'
Requires-Dist: sphinx>=6.0.0; extra == 'docs'
Provides-Extra: domaincolor
Requires-Dist: numpy>=1.20.0; extra == 'domaincolor'
Requires-Dist: pillow>=9.0.0; extra == 'domaincolor'
Requires-Dist: py-domaincolor>=0.1.0; extra == 'domaincolor'
